jsh/__init__.py
jsh/version.py
jsh-0.3.6.dist-info/top_level.txt
jsh-0.3.6.dist-info/METADATA
jsh-0.3.6.dist-info/DESCRIPTION.rst
jsh-0.3.6.dist-info/metadata.json
jsh-0.3.6.dist-info/WHEEL
jsh-0.3.6.dist-info/RECORD
